pytrakem/__init__.py
pytrakem/helpers.py
pytrakem/residuals.py
pytrakem/trakem.py
pytrakem/trakem_classes.py
pytrakem-0.0.1.dist-info/METADATA
pytrakem-0.0.1.dist-info/WHEEL
pytrakem-0.0.1.dist-info/top_level.txt
pytrakem-0.0.1.dist-info/RECORD
